{"clinical_accuracy": "The response must be medically accurate, based on current guidelines and evidence.", "conciseness": "The answer should be brief and to the point, avoiding unnecessary information.", "clarity": "The reasoning should be clearly articulated, making it easy to understand the thought process.", "relevance": "All information provided should be directly relevant to the clinical question posed.", "safety": "The reasoning should prioritize patient safety and consider potential risks in clinical decision-making.", "logical_structure": "The answer should follow a logical progression of thought, making connections between clinical reasoning and conclusions."}